clicommon/__init__.py
clicommon/bcheck.py
clicommon/mlog.py
clicommon/rcmd.py
clicommon-0.3.4.dist-info/METADATA
clicommon-0.3.4.dist-info/WHEEL
clicommon-0.3.4.dist-info/licenses/LICENSE
clicommon-0.3.4.dist-info/RECORD
