Metadata-Version: 2.4
Name: clicommon
Version: 0.3.4
Summary: Python Common Client Library - A collection of useful utilities for command-line applications
Project-URL: Homepage, https://github.com/franksplace/clicommon
Project-URL: Repository, https://github.com/franksplace/clicommon
Project-URL: Issues, https://github.com/franksplace/clicommon/issues
Author-email: Frank Stutz <frank@franksplae.net>
License:                                  Apache License
License-File: LICENSE
Keywords: cli,common,logging,subprocess,utilities
Classifier: Development Status :: 5 - Production/Stable
Classifier: Environment :: Console
Classifier: Intended Audience :: Developers
Classifier: Intended Audience :: Information Technology
Classifier: Intended Audience :: System Administrators
Classifier: License :: OSI Approved :: Apache Software License
Classifier: Operating System :: POSIX :: Linux
Classifier: Programming Language :: Python :: 3
Classifier: Programming Language :: Python :: 3.8
Classifier: Programming Language :: Python :: 3.9
Classifier: Programming Language :: Python :: 3.10
Classifier: Programming Language :: Python :: 3.11
Classifier: Programming Language :: Python :: 3.12
Classifier: Topic :: Software Development :: Libraries :: Python Modules
Classifier: Topic :: System :: Logging
Requires-Python: >=3.8
